qget/__init__.py
qget/__main__.py
qget/qget_aio.py
qget-0.1.7.dist-info/LICENSE
qget-0.1.7.dist-info/METADATA
qget-0.1.7.dist-info/WHEEL
qget-0.1.7.dist-info/top_level.txt
qget-0.1.7.dist-info/RECORD
