Metadata-Version: 2.1
Name: qget
Version: 0.1.7
Summary: Async http(s) downloader
Home-page: https://github.com/dwojtasik/qget
Author: Dominik Wojtasik
Author-email: d.b.wojtasik@gmail.com
License: Apache 2
Project-URL: Bug Tracker, https://github.com/dwojtasik/qget/issues
Classifier: Environment :: Console
Classifier: License :: OSI Approved :: Apache Software License
Classifier: Programming Language :: Python :: 3
Classifier: Programming Language :: Python :: 3.7
Classifier: Programming Language :: Python :: 3.8
Classifier: Programming Language :: Python :: 3.9
Classifier: Programming Language :: Python :: 3.10
Classifier: Operating System :: OS Independent
Classifier: Topic :: Internet :: WWW/HTTP
Classifier: Topic :: System :: Networking
Requires-Python: >=3.7
License-File: LICENSE
Requires-Dist: aiofiles (>=0.8.0)
Requires-Dist: aiohttp (>=3.8.1)
Requires-Dist: aiohttp-socks (>=0.7.1)
Requires-Dist: tqdm (>=4.63.1)
